simplehtmltopdf/__init__.py
simplehtmltopdf/compress.py
simplehtmltopdf/convert.py
simplehtmltopdf-0.0.5.dist-info/METADATA
simplehtmltopdf-0.0.5.dist-info/WHEEL
simplehtmltopdf-0.0.5.dist-info/licenses/LICENSE
simplehtmltopdf-0.0.5.dist-info/RECORD
