Metadata-Version: 2.1
Name: simplehtmltopdf
Version: 0.0.5
Summary: A simple package to print HTML files or URLs to a PDF.
Project-URL: Homepage, https://github.com/KarelKenens/simplehtmltopdf
Project-URL: Issues, https://github.com/KarelKenens/simplehtmltopdf/issues
Author-email: Karel Kenens <karelkenens36@gmail.com>
License-File: LICENSE
Classifier: License :: OSI Approved :: GNU General Public License v3 (GPLv3)
Classifier: Operating System :: OS Independent
Classifier: Programming Language :: Python :: 3
Requires-Python: >=3.12
Requires-Dist: selenium>=4.15.2
